LICENSE
MANIFEST.in
README.rst
setup.cfg
setup.py
nicepay/__init__.py
nicepay/exceptions.py
nicepay/nicepay_backup.py
nicepay/nicepay_v1.py
nicepay/nicepay_v2.py
nicepay.egg-info/PKG-INFO
nicepay.egg-info/SOURCES.txt
nicepay.egg-info/dependency_links.txt
nicepay.egg-info/top_level.txt