Metadata-Version: 1.1
Name: nicepay
Version: 1.1.8
Summary: Python API for nicepay.
Home-page: https://github.com/titipbeliin/nicepay-python/
Author: Agus Makmun (Summon Agus)
Author-email: summon.agus@gmail.com
License: MIT
Download-URL: https://github.com/titipbeliin/nicepay-python/tarball/v1.1.8
Keywords: nicepay,python api
Platform: Linux
Classifier: Development Status :: 5 - Production/Stable
Classifier: License :: OSI Approved :: MIT License
Classifier: Operating System :: POSIX :: Linux
Classifier: Intended Audience :: Developers
Classifier: Programming Language :: Python :: 2
Classifier: Programming Language :: Python :: 2.6
Classifier: Programming Language :: Python :: 2.7
Classifier: Programming Language :: Python :: 3.3
Classifier: Programming Language :: Python :: 3.4
Classifier: Programming Language :: Python :: 3.5
Classifier: Programming Language :: Python :: 3.6
Classifier: Topic :: Software Development
